DESCRIPTION.rst
MANIFEST.in
README.rst
setup.cfg
setup.py
funcache/__init__.py
funcache.egg-info/PKG-INFO
funcache.egg-info/SOURCES.txt
funcache.egg-info/dependency_links.txt
funcache.egg-info/top_level.txt