Metadata-Version: 1.1
Name: funcache
Version: 0.1.2
Summary: Caches function calls.
Home-page: https://github.com/greatcodegroup/funcache
Author: Adrian Letchford
Author-email: me@dradrian.com
License: MIT
Keywords: research,cache,caching,functions
Platform: UNKNOWN
Classifier: Development Status :: 3 - Alpha
Classifier: Intended Audience :: Developers
Classifier: Topic :: Software Development :: Quality Assurance
Classifier: License :: OSI Approved :: MIT License
Classifier: Programming Language :: Python :: 2.7
